mtga_helper/__about__.py
mtga_helper/__init__.py
mtga_helper/__main__.py
mtga_helper/grading.py
mtga_helper/limited.py
mtga_helper/mtg.py
mtga_helper/mtga_log.py
mtga_helper/seventeen_lands.py
mtga_helper-0.2.1.dist-info/METADATA
mtga_helper-0.2.1.dist-info/WHEEL
mtga_helper-0.2.1.dist-info/entry_points.txt
mtga_helper-0.2.1.dist-info/licenses/LICENSE
mtga_helper-0.2.1.dist-info/RECORD
