Metadata-Version: 2.4
Name: mtga_helper
Version: 0.2.1
Summary: CLI application to parse log files from MTGA and analyse them using 17lands data
Project-URL: Homepage, https://github.com/lubosz/python-mtga-helper
Project-URL: Bug Tracker, https://github.com/lubosz/python-mtga-helper/issues
Author-email: Lubosz Sarnecki <lubosz@gmail.com>
Maintainer-email: Lubosz Sarnecki <lubosz@gmail.com>
License-Expression: MIT
License-File: LICENSE
Keywords: 17lands,game,limited,mtg,mtga,tcg
Classifier: Development Status :: 4 - Beta
Classifier: Environment :: Console
Classifier: Intended Audience :: End Users/Desktop
Classifier: License :: OSI Approved :: MIT License
Classifier: Operating System :: OS Independent
Classifier: Programming Language :: Python :: 3
Classifier: Topic :: Games/Entertainment :: Turn Based Strategy
Requires-Python: >=3.0
Requires-Dist: coloredlogs
Requires-Dist: numpy
Requires-Dist: requests
Requires-Dist: scipy
Requires-Dist: tabulate
Requires-Dist: termcolor>=3.1.0
Requires-Dist: wcwidth
Requires-Dist: xdg-base-dirs
